{"chunk_definitions":[{"row":12,"row_count":1,"visible":true,"expansion_state":0,"options":{"engine":"r","include":false,"label":"unnamed-chunk-1"},"document_id":"4234D976","chunk_id":"cv8405jpgtncu","chunk_label":"unnamed-chunk-1"},{"row":23,"row_count":1,"visible":true,"expansion_state":0,"options":{"engine":"r","label":"unnamed-chunk-47"},"document_id":"4234D976","chunk_id":"c8to3e00wippt","chunk_label":"unnamed-chunk-2"},{"row":29,"row_count":1,"visible":true,"expansion_state":0,"options":{"engine":"r","warning":false,"label":"unnamed-chunk-48"},"document_id":"4234D976","chunk_id":"coh2qy5tkn3x6","chunk_label":"unnamed-chunk-3"},{"row":35,"row_count":1,"visible":true,"expansion_state":0,"options":{"engine":"r","label":"unnamed-chunk-49"},"document_id":"4234D976","chunk_id":"cia6p3s1k7b87","chunk_label":"unnamed-chunk-4"},{"row":41,"row_count":1,"visible":true,"expansion_state":0,"options":{"engine":"r","label":"unnamed-chunk-50"},"document_id":"4234D976","chunk_id":"clfr096ju49k5","chunk_label":"unnamed-chunk-5"},{"row":47,"row_count":1,"visible":true,"expansion_state":0,"options":{"engine":"r","label":"unnamed-chunk-52"},"document_id":"4234D976","chunk_id":"cii8jiuvq8jfp","chunk_label":"unnamed-chunk-6"},{"row":56,"row_count":1,"visible":true,"expansion_state":0,"options":{"engine":"r","label":"unnamed-chunk-53"},"document_id":"4234D976","chunk_id":"ca9cygapafj6z","chunk_label":"unnamed-chunk-7"},{"row":62,"row_count":1,"visible":true,"expansion_state":0,"options":{"engine":"r","label":"unnamed-chunk-54"},"document_id":"4234D976","chunk_id":"crnapgyvtasui","chunk_label":"unnamed-chunk-8"},{"row":68,"row_count":1,"visible":true,"expansion_state":0,"options":{"engine":"r","label":"unnamed-chunk-14"},"document_id":"4234D976","chunk_id":"c92zu5eux1hxm","chunk_label":"unnamed-chunk-9"},{"row":74,"row_count":1,"visible":true,"expansion_state":0,"options":{"engine":"r","label":"unnamed-chunk-18"},"document_id":"4234D976","chunk_id":"c1uqri4az9ghz","chunk_label":"unnamed-chunk-10"},{"row":80,"row_count":1,"visible":true,"expansion_state":0,"options":{"engine":"r","label":"unnamed-chunk-19"},"document_id":"4234D976","chunk_id":"c0uncg4j4176u","chunk_label":"unnamed-chunk-11"},{"row":86,"row_count":1,"visible":true,"expansion_state":0,"options":{"engine":"r","label":"unnamed-chunk-20"},"document_id":"4234D976","chunk_id":"cniv9gne1ow0m","chunk_label":"unnamed-chunk-12"},{"row":92,"row_count":1,"visible":true,"expansion_state":0,"options":{"engine":"r","label":"unnamed-chunk-21"},"document_id":"4234D976","chunk_id":"cgpql3xrmumoy","chunk_label":"unnamed-chunk-13"},{"row":101,"row_count":1,"visible":true,"expansion_state":1,"options":{"engine":"r","label":"unnamed-chunk-37"},"document_id":"4234D976","chunk_id":"c0bonbqx13ust","chunk_label":"unnamed-chunk-14"},{"row":107,"row_count":1,"visible":true,"expansion_state":0,"options":{"engine":"r","label":"unnamed-chunk-23"},"document_id":"4234D976","chunk_id":"cb7o7md5vew1g","chunk_label":"unnamed-chunk-15"},{"row":115,"row_count":1,"visible":true,"expansion_state":0,"options":{"engine":"r","label":"unnamed-chunk-43"},"document_id":"4234D976","chunk_id":"c39n95tgufcyi","chunk_label":"unnamed-chunk-16"},{"row":120,"row_count":1,"visible":true,"expansion_state":0,"options":{"engine":"r","label":"unnamed-chunk-44"},"document_id":"4234D976","chunk_id":"c38208cfzuk09","chunk_label":"unnamed-chunk-17"},{"row":126,"row_count":1,"visible":true,"expansion_state":0,"options":{"engine":"r","label":"unnamed-chunk-46"},"document_id":"4234D976","chunk_id":"cj3umgw2vpco5","chunk_label":"unnamed-chunk-18"}],"doc_write_time":1663243064}